scrapi/__init__.py
scrapi/chromium/__init__.py
scrapi/chromium/chromium.py
scrapi/dataset/Clustering_Method.py
scrapi/dataset/Data_Mode.py
scrapi/dataset/Gene_Expression_Dataset.py
scrapi/dataset/Normalization_Method.py
scrapi/dataset/Transformation_Method.py
scrapi/dataset/__init__.py
scrapi/dataset/initialize.py
scrapi/dataset/preprocess.py
scrapi/dataset/utils.py
scrapi/plotting/__init__.py
scrapi/plotting/plotting.py
scrapi/tags/__init__.py
scrapi/tags/tags.py
scrapi/utils/__init__.py
scrapi/utils/fileio.py
scrapi/utils/utils.py
scrapi-0.7.0.dist-info/LICENSE.txt
scrapi-0.7.0.dist-info/METADATA
scrapi-0.7.0.dist-info/WHEEL
scrapi-0.7.0.dist-info/entry_points.txt
scrapi-0.7.0.dist-info/top_level.txt
scrapi-0.7.0.dist-info/RECORD
